vizdxp/__init__.py
vizdxp/__main__.py
vizdxp/app.py
vizdxp/graphs.py
vizdxp/style.css
vizdxp-0.2.2.data/data/style.css
vizdxp-0.2.2.dist-info/LICENSE
vizdxp-0.2.2.dist-info/METADATA
vizdxp-0.2.2.dist-info/WHEEL
vizdxp-0.2.2.dist-info/entry_points.txt
vizdxp-0.2.2.dist-info/top_level.txt
vizdxp-0.2.2.dist-info/RECORD
