Metadata-Version: 2.1
Name: vizdxp
Version: 0.2.2
Summary: Simple data visualization web app
Home-page: https://github.com/Vinothsuku/vizdxp
Author: vinoth sukumaran
Author-email: vinoth.suku@gmail.com
License: UNKNOWN
Platform: UNKNOWN
Classifier: Programming Language :: Python :: 3
Classifier: License :: OSI Approved :: MIT License
Classifier: Operating System :: OS Independent
Requires-Python: >=3.6
Requires-Dist: streamlit (>=1.37.1)
Requires-Dist: pandas (>=1.1.0)
Requires-Dist: numpy (>=1.19.1)
Requires-Dist: plotly (>=4.9.0)
